odoo8_addon_website_portal-8.0.1.0.0.99.dev39-py3.8-nspkg.pth
odoo_addons/website_portal/README.rst
odoo_addons/website_portal/__init__.py
odoo_addons/website_portal/__openerp__.py
odoo_addons/website_portal/controllers/__init__.py
odoo_addons/website_portal/controllers/main.py
odoo_addons/website_portal/i18n/af.po
odoo_addons/website_portal/i18n/ar.po
odoo_addons/website_portal/i18n/bg.po
odoo_addons/website_portal/i18n/ca.po
odoo_addons/website_portal/i18n/da.po
odoo_addons/website_portal/i18n/de.po
odoo_addons/website_portal/i18n/el.po
odoo_addons/website_portal/i18n/el_GR.po
odoo_addons/website_portal/i18n/es.po
odoo_addons/website_portal/i18n/es_CO.po
odoo_addons/website_portal/i18n/es_DO.po
odoo_addons/website_portal/i18n/es_EC.po
odoo_addons/website_portal/i18n/es_MX.po
odoo_addons/website_portal/i18n/es_PE.po
odoo_addons/website_portal/i18n/es_VE.po
odoo_addons/website_portal/i18n/et.po
odoo_addons/website_portal/i18n/eu.po
odoo_addons/website_portal/i18n/fa.po
odoo_addons/website_portal/i18n/fi.po
odoo_addons/website_portal/i18n/fr.po
odoo_addons/website_portal/i18n/he.po
odoo_addons/website_portal/i18n/hr.po
odoo_addons/website_portal/i18n/hu.po
odoo_addons/website_portal/i18n/id.po
odoo_addons/website_portal/i18n/it.po
odoo_addons/website_portal/i18n/ka.po
odoo_addons/website_portal/i18n/kab.po
odoo_addons/website_portal/i18n/ko.po
odoo_addons/website_portal/i18n/lv.po
odoo_addons/website_portal/i18n/mk.po
odoo_addons/website_portal/i18n/mn.po
odoo_addons/website_portal/i18n/nb.po
odoo_addons/website_portal/i18n/nl.po
odoo_addons/website_portal/i18n/nl_BE.po
odoo_addons/website_portal/i18n/nl_NL.po
odoo_addons/website_portal/i18n/pl.po
odoo_addons/website_portal/i18n/pt.po
odoo_addons/website_portal/i18n/pt_BR.po
odoo_addons/website_portal/i18n/ro.po
odoo_addons/website_portal/i18n/ru.po
odoo_addons/website_portal/i18n/sk.po
odoo_addons/website_portal/i18n/sl.po
odoo_addons/website_portal/i18n/sv.po
odoo_addons/website_portal/i18n/th.po
odoo8_addon_website_portal-8.0.1.0.0.99.dev39.dist-info/METADATA
odoo8_addon_website_portal-8.0.1.0.0.99.dev39.dist-info/WHEEL
odoo8_addon_website_portal-8.0.1.0.0.99.dev39.dist-info/namespace_packages.txt
odoo8_addon_website_portal-8.0.1.0.0.99.dev39.dist-info/top_level.txt
odoo8_addon_website_portal-8.0.1.0.0.99.dev39.dist-info/RECORD
