Metadata-Version: 2.1
Name: odoo8-addon-website-portal
Version: 8.0.1.0.0.99.dev39
Summary: Account Management Frontend for your Customers
Home-page: https://www.odoo.com/, http://www.wearemonk.com, https://github.com/OCA/website
Author: Odoo SA, MONK Software, Antiun Ingeniería S.L.
License: LGPL-3
Platform: UNKNOWN
Classifier: Programming Language :: Python
Classifier: Framework :: Odoo
Classifier: Framework :: Odoo :: 8.0
Classifier: License :: OSI Approved :: GNU Lesser General Public License v3 (LGPLv3)
Requires-Python: ~=2.7
Requires-Dist: odoo (<9.0a,>=8.0a)
